timestep/__init__.py
timestep/_vendored_imports.py
timestep/_vendored/__init__.py
timestep/_vendored/agents/__init__.py
timestep/_vendored/agents/_config.py
timestep/_vendored/agents/_debug.py
timestep/_vendored/agents/_run_impl.py
timestep/_vendored/agents/agent.py
timestep/_vendored/agents/agent_output.py
timestep/_vendored/agents/apply_diff.py
timestep/_vendored/agents/computer.py
timestep/_vendored/agents/editor.py
timestep/_vendored/agents/exceptions.py
timestep/_vendored/agents/function_schema.py
timestep/_vendored/agents/guardrail.py
timestep/_vendored/agents/items.py
timestep/_vendored/agents/lifecycle.py
timestep/_vendored/agents/logger.py
timestep/_vendored/agents/model_settings.py
timestep/_vendored/agents/prompts.py
timestep/_vendored/agents/py.typed
timestep/_vendored/agents/repl.py
timestep/_vendored/agents/result.py
timestep/_vendored/agents/run.py
timestep/_vendored/agents/run_context.py
timestep/_vendored/agents/run_state.py
timestep/_vendored/agents/stream_events.py
timestep/_vendored/agents/strict_schema.py
timestep/_vendored/agents/tool.py
timestep/_vendored/agents/tool_context.py
timestep/_vendored/agents/tool_guardrails.py
timestep/_vendored/agents/usage.py
timestep/_vendored/agents/version.py
timestep/_vendored/agents/extensions/__init__.py
timestep/_vendored/agents/extensions/handoff_filters.py
timestep/_vendored/agents/extensions/handoff_prompt.py
timestep/_vendored/agents/extensions/visualization.py
timestep/_vendored/agents/extensions/memory/__init__.py
timestep/_vendored/agents/extensions/memory/advanced_sqlite_session.py
timestep/_vendored/agents/extensions/memory/dapr_session.py
timestep/_vendored/agents/extensions/memory/encrypt_session.py
timestep/_vendored/agents/extensions/memory/redis_session.py
timestep/_vendored/agents/extensions/memory/sqlalchemy_session.py
timestep/_vendored/agents/extensions/models/__init__.py
timestep/_vendored/agents/extensions/models/litellm_model.py
timestep-2026.0.57.dist-info/METADATA
timestep-2026.0.57.dist-info/WHEEL
timestep-2026.0.57.dist-info/RECORD
