Metadata-Version: 2.4
Name: timestep
Version: 2026.0.57
Summary: Timestep AI - Agent execution framework with cross-language state persistence and multi-model support for OpenAI Agents
License: MIT
Requires-Python: >=3.11
Requires-Dist: asyncpg>=0.29.0
Requires-Dist: firecrawl-py>=1.0.0
Requires-Dist: griffe<2,>=1.5.6
Requires-Dist: jinja2>=3.0.0
Requires-Dist: mcp<2,>=1.11.0; python_version >= '3.10'
Requires-Dist: ollama>=0.6.1
Requires-Dist: openai<3,>=2.9.0
Requires-Dist: pydantic<3,>=2.12.3
Requires-Dist: pytest-asyncio>=0.21.0
Requires-Dist: pytest>=7.0.0
Requires-Dist: requests<3,>=2.0
Requires-Dist: types-requests<3,>=2.0
Requires-Dist: typing-extensions<5,>=4.12.2
